Metadata-Version: 2.4
Name: spotinst-sdk2
Version: 3.22.0
Summary: A Python SDK for Spotinst
Home-page: https://github.com/spotinst/spotinst-sdk-python
Author: Spotinst
Author-email: service@spotinst.com
License: MIT
Keywords: spotinst spot instances aws azure ec2 cloud infrastructure development elastigroup
Classifier: Development Status :: 5 - Production/Stable
Classifier: Intended Audience :: Developers
Classifier: Topic :: Software Development :: Libraries :: Python Modules
Classifier: License :: OSI Approved :: MIT License
Classifier: Programming Language :: Python :: 3.7
Classifier: Programming Language :: Python :: 3.8
Classifier: Programming Language :: Python :: 3.9
Classifier: Programming Language :: Python :: 3.10
Classifier: Programming Language :: Python :: 3.11
Requires-Python: >=3.7.0
License-File: LICENSE
License-File: NOTICE.md
Requires-Dist: requests
Requires-Dist: PyYaml
Dynamic: author
Dynamic: author-email
Dynamic: classifier
Dynamic: description
Dynamic: description-content-type
Dynamic: home-page
Dynamic: keywords
Dynamic: license
Dynamic: license-file
Dynamic: requires-dist
Dynamic: requires-python
Dynamic: summary
